linktune/__init__.py
linktune/setup.py
linktune/api/__init__.py
linktune/api/applemusic.py
linktune/api/convert.py
linktune/api/deezer.py
linktune/api/search.py
linktune/api/spotify.py
linktune/api/tidal.py
linktune/api/youtube.py
linktune/cli/__init__.py
linktune/cli/arguments.py
linktune/cli/commands.py
linktune/cli/main.py
linktune/config/config.py
linktune/web/app.py
linktune-0.1.3.dist-info/LICENCE
linktune-0.1.3.dist-info/METADATA
linktune-0.1.3.dist-info/WHEEL
linktune-0.1.3.dist-info/entry_points.txt
linktune-0.1.3.dist-info/top_level.txt
linktune-0.1.3.dist-info/RECORD
