Metadata-Version: 2.1
Name: linktune
Version: 0.1.3
Summary: A package for searching and converting music links across different music streaming services.
Author-email: fi <fiona.nugent7@gmail.com>
License: MIT License
Project-URL: Homepage, https://github.com/kattums/LinkTune
Project-URL: Bug Tracker, https://github.com/kattums/LinkTune/issues
Requires-Python: >=3.7
License-File: LICENCE
Requires-Dist: spotipy (~=2.22.0)
Requires-Dist: tidal-unofficial (~=0.1.0)
Requires-Dist: ytmusicapi (~=0.25.0)
